dominix/__init__.py
dominix/_version.py
dominix/document.py
dominix/dom1core.py
dominix/dom_tag.py
dominix/svg.py
dominix/tags.py
dominix/util.py
dominix-2.0.1.dist-info/LICENSE.txt
dominix-2.0.1.dist-info/METADATA
dominix-2.0.1.dist-info/WHEEL
dominix-2.0.1.dist-info/top_level.txt
dominix-2.0.1.dist-info/RECORD
