Metadata-Version: 2.1
Name: dominix
Version: 2.0.1
Summary: Dominix is a fork of Dominate that adds support for HTMX and Alpine.js. (Dominate is a Python library for creating and manipulating HTML documents using an elegant DOM API.)
Author: Tom Flanagan, Jake Wharton, Are Meisfjord
License: LGPL-3.0-or-newer
Project-URL: Homepage, https://github.com/aremeis/dominix
Project-URL: Source, https://github.com/aremeis/dominix
Keywords: framework,templating,template,html,xhtml,python,html5
Classifier: Intended Audience :: Developers
Classifier: License :: OSI Approved :: GNU Lesser General Public License v3 (LGPLv3)
Classifier: Operating System :: OS Independent
Classifier: Programming Language :: Python
Classifier: Programming Language :: Python :: 3
Classifier: Programming Language :: Python :: 3.7
Classifier: Programming Language :: Python :: 3.8
Classifier: Programming Language :: Python :: 3.9
Classifier: Programming Language :: Python :: 3.10
Classifier: Programming Language :: Python :: 3.11
Classifier: Programming Language :: Python :: 3.12
Classifier: Programming Language :: Python :: Implementation :: PyPy
Classifier: Topic :: Internet :: WWW/HTTP :: Dynamic Content
Classifier: Topic :: Software Development :: Libraries :: Python Modules
Classifier: Topic :: Text Processing :: Markup :: HTML
Requires-Python: >=3.4
License-File: LICENSE.txt
